{
  "stats": {
    "suites": 8,
    "tests": 17,
    "passes": 17,
    "pending": 0,
    "failures": 0,
    "start": "2025-11-21T09:09:43.065Z",
    "end": "2025-11-21T09:10:01.891Z",
    "duration": 18826,
    "testsRegistered": 17,
    "passPercent": 100,
    "pendingPercent": 0,
    "other": 0,
    "hasOther": false,
    "skipped": 0,
    "hasSkipped": false
  },
  "results": [
    {
      "uuid": "b4b03b14-693f-4e96-adb7-6ac2ba880637",
      "title": "",
      "fullFile": "cypress/e2e/customer/customerDashboard.cy.js",
      "file": "cypress/e2e/customer/customerDashboard.cy.js",
      "beforeHooks": [],
      "afterHooks": [],
      "tests": [],
      "suites": [
        {
          "uuid": "db54302e-5586-4822-9589-a560e5d0036d",
          "title": "Customer Dashboard Tests",
          "fullFile": "",
          "file": "",
          "beforeHooks": [],
          "afterHooks": [],
          "tests": [],
          "suites": [
            {
              "uuid": "6e21e388-0059-4420-8ec0-a88aa5120cc2",
              "title": "Dashboard UI Elements",
              "fullFile": "",
              "file": "",
              "beforeHooks": [],
              "afterHooks": [],
              "tests": [
                {
                  "title": "should display all dashboard elements",
                  "fullTitle": "Customer Dashboard Tests Dashboard UI Elements should display all dashboard elements",
                  "timedOut": null,
                  "duration": 2369,
                  "state": "passed",
                  "speed": "fast",
                  "pass": true,
                  "fail": false,
                  "pending": false,
                  "context": null,
                  "code": "_apiHelpers.default.mockGetCustomers([]);\n_apiHelpers.default.waitForApi('getCustomers');\ndashboardPage.verifyDashboardElements();\ndashboardPage.verifySidebarElements();",
                  "err": {},
                  "uuid": "36ede138-0450-4875-b3f9-2cc687413228",
                  "parentUUID": "6e21e388-0059-4420-8ec0-a88aa5120cc2",
                  "isHook": false,
                  "skipped": false
                },
                {
                  "title": "should display table headers correctly",
                  "fullTitle": "Customer Dashboard Tests Dashboard UI Elements should display table headers correctly",
                  "timedOut": null,
                  "duration": 837,
                  "state": "passed",
                  "speed": "fast",
                  "pass": true,
                  "fail": false,
                  "pending": false,
                  "context": null,
                  "code": "_apiHelpers.default.mockGetCustomers(testData.validCustomers);\n_apiHelpers.default.waitForApi('getCustomers');\ndashboardPage.verifyTableHeaders();",
                  "err": {},
                  "uuid": "9651d925-f9c6-43c3-9852-0b48870fda80",
                  "parentUUID": "6e21e388-0059-4420-8ec0-a88aa5120cc2",
                  "isHook": false,
                  "skipped": false
                }
              ],
              "suites": [],
              "passes": [
                "36ede138-0450-4875-b3f9-2cc687413228",
                "9651d925-f9c6-43c3-9852-0b48870fda80"
              ],
              "failures": [],
              "pending": [],
              "skipped": [],
              "duration": 3206,
              "root": false,
              "rootEmpty": false,
              "_timeout": 2000
            },
            {
              "uuid": "3aa89249-50e7-43fc-8297-6832758088a1",
              "title": "Customer Data Display",
              "fullFile": "",
              "file": "",
              "beforeHooks": [],
              "afterHooks": [],
              "tests": [
                {
                  "title": "should load and display customer data",
                  "fullTitle": "Customer Dashboard Tests Customer Data Display should load and display customer data",
                  "timedOut": null,
                  "duration": 817,
                  "state": "passed",
                  "speed": "fast",
                  "pass": true,
                  "fail": false,
                  "pending": false,
                  "context": null,
                  "code": "_apiHelpers.default.mockGetCustomers(testData.validCustomers);\n_apiHelpers.default.waitForApi('getCustomers');\ntestData.validCustomers.forEach(customer => {\n  dashboardPage.verifyCustomerExists(customer.name);\n  dashboardPage.verifyCustomerExists(customer.email);\n});",
                  "err": {},
                  "uuid": "42ad2441-4428-4204-9de9-a3022cffeea9",
                  "parentUUID": "3aa89249-50e7-43fc-8297-6832758088a1",
                  "isHook": false,
                  "skipped": false
                },
                {
                  "title": "should show no data message when no customers exist",
                  "fullTitle": "Customer Dashboard Tests Customer Data Display should show no data message when no customers exist",
                  "timedOut": null,
                  "duration": 560,
                  "state": "passed",
                  "speed": "fast",
                  "pass": true,
                  "fail": false,
                  "pending": false,
                  "context": null,
                  "code": "_apiHelpers.default.mockGetCustomers([]);\n_apiHelpers.default.waitForApi('getCustomers');\ndashboardPage.verifyNoDataMessage();",
                  "err": {},
                  "uuid": "ab67743a-24a1-4db5-8f61-e02363776df7",
                  "parentUUID": "3aa89249-50e7-43fc-8297-6832758088a1",
                  "isHook": false,
                  "skipped": false
                },
                {
                  "title": "should show loading state",
                  "fullTitle": "Customer Dashboard Tests Customer Data Display should show loading state",
                  "timedOut": null,
                  "duration": 2535,
                  "state": "passed",
                  "speed": "fast",
                  "pass": true,
                  "fail": false,
                  "pending": false,
                  "context": null,
                  "code": "_apiHelpers.default.mockDelayedResponse('GET', 'customer', {\n  data: []\n}, 2000);\ndashboardPage.verifyLoadingState();\n_apiHelpers.default.waitForApi('delayedResponse');",
                  "err": {},
                  "uuid": "d70a846d-c9ff-4222-8245-4baba8304eed",
                  "parentUUID": "3aa89249-50e7-43fc-8297-6832758088a1",
                  "isHook": false,
                  "skipped": false
                }
              ],
              "suites": [],
              "passes": [
                "42ad2441-4428-4204-9de9-a3022cffeea9",
                "ab67743a-24a1-4db5-8f61-e02363776df7",
                "d70a846d-c9ff-4222-8245-4baba8304eed"
              ],
              "failures": [],
              "pending": [],
              "skipped": [],
              "duration": 3912,
              "root": false,
              "rootEmpty": false,
              "_timeout": 2000
            },
            {
              "uuid": "b5de6c4d-c7fd-4750-9cbc-15cb1965bf09",
              "title": "Customer Navigation",
              "fullFile": "",
              "file": "",
              "beforeHooks": [],
              "afterHooks": [],
              "tests": [
                {
                  "title": "should navigate to add customer page",
                  "fullTitle": "Customer Dashboard Tests Customer Navigation should navigate to add customer page",
                  "timedOut": null,
                  "duration": 1076,
                  "state": "passed",
                  "speed": "fast",
                  "pass": true,
                  "fail": false,
                  "pending": false,
                  "context": null,
                  "code": "_apiHelpers.default.mockGetCustomers([]);\n_apiHelpers.default.waitForApi('getCustomers');\ndashboardPage.clickAddNewCustomer();\ndashboardPage.verifyUrl('/addCustomer');",
                  "err": {},
                  "uuid": "fbd98ce2-b3d0-451e-91bf-e18821c89b8c",
                  "parentUUID": "b5de6c4d-c7fd-4750-9cbc-15cb1965bf09",
                  "isHook": false,
                  "skipped": false
                },
                {
                  "title": "should navigate to edit customer page",
                  "fullTitle": "Customer Dashboard Tests Customer Navigation should navigate to edit customer page",
                  "timedOut": null,
                  "duration": 724,
                  "state": "passed",
                  "speed": "fast",
                  "pass": true,
                  "fail": false,
                  "pending": false,
                  "context": null,
                  "code": "const customer = testData.validCustomers[0];\n_apiHelpers.default.mockGetCustomers([customer]);\n_apiHelpers.default.waitForApi('getCustomers');\ndashboardPage.clickEditCustomer(customer.name);\ndashboardPage.verifyUrl(`/addCustomer/${customer._id}`);",
                  "err": {},
                  "uuid": "68e7328d-38d9-43b3-a6d5-59d5c5f5668a",
                  "parentUUID": "b5de6c4d-c7fd-4750-9cbc-15cb1965bf09",
                  "isHook": false,
                  "skipped": false
                },
                {
                  "title": "should navigate back with back arrow",
                  "fullTitle": "Customer Dashboard Tests Customer Navigation should navigate back with back arrow",
                  "timedOut": null,
                  "duration": 1209,
                  "state": "passed",
                  "speed": "fast",
                  "pass": true,
                  "fail": false,
                  "pending": false,
                  "context": null,
                  "code": "_apiHelpers.default.mockGetCustomers([]);\n_apiHelpers.default.waitForApi('getCustomers');\ndashboardPage.clickBackButton();\ndashboardPage.verifyUrl('');",
                  "err": {},
                  "uuid": "8e6b715e-557f-412c-a409-692abd229d45",
                  "parentUUID": "b5de6c4d-c7fd-4750-9cbc-15cb1965bf09",
                  "isHook": false,
                  "skipped": false
                }
              ],
              "suites": [],
              "passes": [
                "fbd98ce2-b3d0-451e-91bf-e18821c89b8c",
                "68e7328d-38d9-43b3-a6d5-59d5c5f5668a",
                "8e6b715e-557f-412c-a409-692abd229d45"
              ],
              "failures": [],
              "pending": [],
              "skipped": [],
              "duration": 3009,
              "root": false,
              "rootEmpty": false,
              "_timeout": 2000
            },
            {
              "uuid": "5b55db7b-2220-4038-add6-fed0f293c353",
              "title": "Pagination",
              "fullFile": "",
              "file": "",
              "beforeHooks": [],
              "afterHooks": [],
              "tests": [
                {
                  "title": "should handle pagination correctly",
                  "fullTitle": "Customer Dashboard Tests Pagination should handle pagination correctly",
                  "timedOut": null,
                  "duration": 830,
                  "state": "passed",
                  "speed": "fast",
                  "pass": true,
                  "fail": false,
                  "pending": false,
                  "context": null,
                  "code": "const paginationData = _dataGenerators.default.generatePaginationData(15);\n_apiHelpers.default.mockGetCustomers(paginationData);\n_apiHelpers.default.waitForApi('getCustomers');\n// Verify pagination buttons exist\ncy.contains('button', '1').should('be.visible');\ncy.contains('button', '2').should('be.visible');\n// Click page 2\ndashboardPage.clickPaginationPage(2);\ndashboardPage.verifyPaginationActive(2);",
                  "err": {},
                  "uuid": "d4d91b99-a493-42bd-9868-65c3993f57f7",
                  "parentUUID": "5b55db7b-2220-4038-add6-fed0f293c353",
                  "isHook": false,
                  "skipped": false
                }
              ],
              "suites": [],
              "passes": [
                "d4d91b99-a493-42bd-9868-65c3993f57f7"
              ],
              "failures": [],
              "pending": [],
              "skipped": [],
              "duration": 830,
              "root": false,
              "rootEmpty": false,
              "_timeout": 2000
            },
            {
              "uuid": "099d6172-17ca-43a4-98b1-1e7b06e35e05",
              "title": "Export Functionality",
              "fullFile": "",
              "file": "",
              "beforeHooks": [],
              "afterHooks": [],
              "tests": [
                {
                  "title": "should show alert when exporting with no data",
                  "fullTitle": "Customer Dashboard Tests Export Functionality should show alert when exporting with no data",
                  "timedOut": null,
                  "duration": 752,
                  "state": "passed",
                  "speed": "fast",
                  "pass": true,
                  "fail": false,
                  "pending": false,
                  "context": null,
                  "code": "_apiHelpers.default.mockGetCustomers([]);\n_apiHelpers.default.waitForApi('getCustomers');\ncy.stubWindowMethods({\n  alert: true\n});\ndashboardPage.clickExportExcel();\ncy.get('@alertStub').should('be.calledWith', 'No data available to export!');",
                  "err": {},
                  "uuid": "7c075b7d-4871-4007-9721-be98871d06b9",
                  "parentUUID": "099d6172-17ca-43a4-98b1-1e7b06e35e05",
                  "isHook": false,
                  "skipped": false
                }
              ],
              "suites": [],
              "passes": [
                "7c075b7d-4871-4007-9721-be98871d06b9"
              ],
              "failures": [],
              "pending": [],
              "skipped": [],
              "duration": 752,
              "root": false,
              "rootEmpty": false,
              "_timeout": 2000
            },
            {
              "uuid": "9893c439-107c-4601-9671-f225827e4dc1",
              "title": "Error Handling",
              "fullFile": "",
              "file": "",
              "beforeHooks": [],
              "afterHooks": [],
              "tests": [
                {
                  "title": "should handle API server error gracefully",
                  "fullTitle": "Customer Dashboard Tests Error Handling should handle API server error gracefully",
                  "timedOut": null,
                  "duration": 653,
                  "state": "passed",
                  "speed": "fast",
                  "pass": true,
                  "fail": false,
                  "pending": false,
                  "context": null,
                  "code": "_apiHelpers.default.mockServerError('GET', 'customer');\n_apiHelpers.default.waitForApi('serverError');\n// Component should not crash\ncy.get('body').should('exist');\ncy.get('table').should('exist');",
                  "err": {},
                  "uuid": "f8617b82-60eb-4384-8615-fd3cf586ba57",
                  "parentUUID": "9893c439-107c-4601-9671-f225827e4dc1",
                  "isHook": false,
                  "skipped": false
                },
                {
                  "title": "should handle network errors",
                  "fullTitle": "Customer Dashboard Tests Error Handling should handle network errors",
                  "timedOut": null,
                  "duration": 548,
                  "state": "passed",
                  "speed": "fast",
                  "pass": true,
                  "fail": false,
                  "pending": false,
                  "context": null,
                  "code": "_apiHelpers.default.mockNetworkError('GET', 'customer');\n_apiHelpers.default.waitForApi('networkError');\ncy.get('body').should('exist');",
                  "err": {},
                  "uuid": "4c3a1938-6d81-4255-88b0-f6518fe5d0cc",
                  "parentUUID": "9893c439-107c-4601-9671-f225827e4dc1",
                  "isHook": false,
                  "skipped": false
                },
                {
                  "title": "should handle delete error gracefully",
                  "fullTitle": "Customer Dashboard Tests Error Handling should handle delete error gracefully",
                  "timedOut": null,
                  "duration": 684,
                  "state": "passed",
                  "speed": "fast",
                  "pass": true,
                  "fail": false,
                  "pending": false,
                  "context": null,
                  "code": "const customer = testData.validCustomers[0];\n_apiHelpers.default.mockGetCustomers([customer]);\n_apiHelpers.default.waitForApi('getCustomers');\n_apiHelpers.default.mockServerError('DELETE', `customer/${customer._id}`, 'deleteError');\ncy.stubWindowMethods({\n  confirm: true,\n  alert: true\n});\ndashboardPage.clickDeleteCustomer(customer.name);\n_apiHelpers.default.waitForApi('deleteError');\ncy.get('@alertStub').should('be.calledWith', 'Failed to delete customer.');\n// Customer should still be visible\ndashboardPage.verifyCustomerExists(customer.name);",
                  "err": {},
                  "uuid": "15279c9b-d06b-4c98-82a4-e74551671ff5",
                  "parentUUID": "9893c439-107c-4601-9671-f225827e4dc1",
                  "isHook": false,
                  "skipped": false
                }
              ],
              "suites": [],
              "passes": [
                "f8617b82-60eb-4384-8615-fd3cf586ba57",
                "4c3a1938-6d81-4255-88b0-f6518fe5d0cc",
                "15279c9b-d06b-4c98-82a4-e74551671ff5"
              ],
              "failures": [],
              "pending": [],
              "skipped": [],
              "duration": 1885,
              "root": false,
              "rootEmpty": false,
              "_timeout": 2000
            },
            {
              "uuid": "91256838-6b0f-4f65-9a49-73769fa632ff",
              "title": "Edge Cases",
              "fullFile": "",
              "file": "",
              "beforeHooks": [],
              "afterHooks": [],
              "tests": [
                {
                  "title": "should handle very long customer names",
                  "fullTitle": "Customer Dashboard Tests Edge Cases should handle very long customer names",
                  "timedOut": null,
                  "duration": 533,
                  "state": "passed",
                  "speed": "fast",
                  "pass": true,
                  "fail": false,
                  "pending": false,
                  "context": null,
                  "code": "const longNameCustomer = _dataGenerators.default.generateEdgeCaseData('longName');\n_apiHelpers.default.mockGetCustomers([longNameCustomer]);\n_apiHelpers.default.waitForApi('getCustomers');\n// Should display without breaking UI\ncy.contains(longNameCustomer.name.substring(0, 50)).should('be.visible');",
                  "err": {},
                  "uuid": "c0958978-6c4b-4a9e-8149-6c6d01a5d067",
                  "parentUUID": "91256838-6b0f-4f65-9a49-73769fa632ff",
                  "isHook": false,
                  "skipped": false
                },
                {
                  "title": "should handle special characters in search",
                  "fullTitle": "Customer Dashboard Tests Edge Cases should handle special characters in search",
                  "timedOut": null,
                  "duration": 1676,
                  "state": "passed",
                  "speed": "fast",
                  "pass": true,
                  "fail": false,
                  "pending": false,
                  "context": null,
                  "code": "_apiHelpers.default.mockGetCustomers([]);\n_apiHelpers.default.waitForApi('getCustomers');\ndashboardPage.searchCustomer('@#$%');\ncy.get('body').should('exist'); // No crash",
                  "err": {},
                  "uuid": "c9961ff2-5644-4c59-88f4-54ea4c117873",
                  "parentUUID": "91256838-6b0f-4f65-9a49-73769fa632ff",
                  "isHook": false,
                  "skipped": false
                },
                {
                  "title": "should handle rapid sequential searches",
                  "fullTitle": "Customer Dashboard Tests Edge Cases should handle rapid sequential searches",
                  "timedOut": null,
                  "duration": 1374,
                  "state": "passed",
                  "speed": "fast",
                  "pass": true,
                  "fail": false,
                  "pending": false,
                  "context": null,
                  "code": "_apiHelpers.default.mockGetCustomers([]);\n_apiHelpers.default.waitForApi('getCustomers');\ncy.get('input[placeholder=\"Search Customer...\"]').clear().type('A', {\n  delay: 50\n}).type('B', {\n  delay: 50\n}).type('C', {\n  delay: 50\n}).clear().type('D', {\n  delay: 50\n});\ncy.get('body').should('exist');",
                  "err": {},
                  "uuid": "950ffff0-9cb4-412a-a8a8-fe44302e1238",
                  "parentUUID": "91256838-6b0f-4f65-9a49-73769fa632ff",
                  "isHook": false,
                  "skipped": false
                },
                {
                  "title": "should handle empty response gracefully",
                  "fullTitle": "Customer Dashboard Tests Edge Cases should handle empty response gracefully",
                  "timedOut": null,
                  "duration": 519,
                  "state": "passed",
                  "speed": "fast",
                  "pass": true,
                  "fail": false,
                  "pending": false,
                  "context": null,
                  "code": "cy.intercept('GET', `${dashboardPage.apiUrl}/customer`, {\n  statusCode: 200,\n  body: {\n    data: null\n  }\n}).as('emptyResponse');\ncy.wait('@emptyResponse');\ncy.get('body').should('exist');",
                  "err": {},
                  "uuid": "603db1eb-3461-4cda-8fe5-e17fab46ebbf",
                  "parentUUID": "91256838-6b0f-4f65-9a49-73769fa632ff",
                  "isHook": false,
                  "skipped": false
                }
              ],
              "suites": [],
              "passes": [
                "c0958978-6c4b-4a9e-8149-6c6d01a5d067",
                "c9961ff2-5644-4c59-88f4-54ea4c117873",
                "950ffff0-9cb4-412a-a8a8-fe44302e1238",
                "603db1eb-3461-4cda-8fe5-e17fab46ebbf"
              ],
              "failures": [],
              "pending": [],
              "skipped": [],
              "duration": 4102,
              "root": false,
              "rootEmpty": false,
              "_timeout": 2000
            }
          ],
          "passes": [],
          "failures": [],
          "pending": [],
          "skipped": [],
          "duration": 0,
          "root": false,
          "rootEmpty": false,
          "_timeout": 2000
        }
      ],
      "passes": [],
      "failures": [],
      "pending": [],
      "skipped": [],
      "duration": 0,
      "root": true,
      "rootEmpty": true,
      "_timeout": 2000
    }
  ],
  "meta": {
    "mocha": {
      "version": "7.2.0"
    },
    "mochawesome": {
      "options": {
        "quiet": false,
        "reportFilename": "[status]_[datetime]-[name]-report",
        "saveHtml": true,
        "saveJson": true,
        "consoleReporter": "spec",
        "useInlineDiffs": false,
        "code": true
      },
      "version": "7.1.4"
    },
    "marge": {
      "options": {
        "reportDir": "cypress/reports",
        "overwrite": false,
        "html": true,
        "json": true,
        "timestamp": "mmddyyyy_HHMMss",
        "screenshots": true,
        "embeddedScreenshots": true,
        "inlineAssets": true,
        "saveJson": true,
        "saveHtml": true,
        "reportFilename": "[status]_[datetime]-[name]-report",
        "charts": true
      },
      "version": "6.3.2"
    }
  }
}